{
  "products": [
    {
      "id": "xyz1",
      "name": "Milk",
      "price": 29.9,
      "category": "Dairy",
      "rating": 3

    },
    {
      "id": "xyz2",
      "name": "Bread",
      "price": 5.9,
      "category": "Pastries",
      "rating": 4
    },
    {
      "id": "xyz3",
      "name": "Cheese",
      "price": 29.9,
      "category": "Dairy",
      "rating": 3
    },
    {
      "id": "xyz4",
      "name": "Croissant",
      "price": 7.5,
      "category": "Pastries",
      "rating": 5
    },
    {
      "id": "xyz5",
      "name": "Orange Juice",
      "price": 5.8,
      "category": "Beverage",
      "rating": 5
    },
    {
      "id": "xyz6",
      "name": "Coca Cola",
      "price": 6.0,
      "category": "Beverage",
      "rating": 4
    }
  ]
}